BiteBiKaifazheZhinan/README.md
BiteBiKaifazheZhinan/__init__.py
BiteBiKaifazheZhinan/__main__.py
BiteBiKaifazheZhinan/file.epub
BiteBiKaifazheZhinan/index.html
BiteBiKaifazheZhinan/css/__init__.py
BiteBiKaifazheZhinan/css/annotations.css
BiteBiKaifazheZhinan/css/main.css
BiteBiKaifazheZhinan/css/normalize.css
BiteBiKaifazheZhinan/css/popup.css
BiteBiKaifazheZhinan/font/__init__.py
BiteBiKaifazheZhinan/font/fontello.eot
BiteBiKaifazheZhinan/font/fontello.svg
BiteBiKaifazheZhinan/font/fontello.ttf
BiteBiKaifazheZhinan/font/fontello.woff
BiteBiKaifazheZhinan/img/__init__.py
BiteBiKaifazheZhinan/img/annotator-glyph-sprite.png
BiteBiKaifazheZhinan/img/annotator-icon-sprite.png
BiteBiKaifazheZhinan/img/apple-touch-icon.png
BiteBiKaifazheZhinan/img/cancelfullscreen.png
BiteBiKaifazheZhinan/img/close.png
BiteBiKaifazheZhinan/img/fullscreen.png
BiteBiKaifazheZhinan/img/loader.gif
BiteBiKaifazheZhinan/img/menu-icon.png
BiteBiKaifazheZhinan/img/save.png
BiteBiKaifazheZhinan/img/saved.png
BiteBiKaifazheZhinan/img/settings-s.png
BiteBiKaifazheZhinan/img/settings.png
BiteBiKaifazheZhinan/img/star.png
BiteBiKaifazheZhinan/js/__init__.py
BiteBiKaifazheZhinan/js/epub.js
BiteBiKaifazheZhinan/js/epub.min.js
BiteBiKaifazheZhinan/js/epub.min.map
BiteBiKaifazheZhinan/js/hooks.min.js
BiteBiKaifazheZhinan/js/hooks.min.map
BiteBiKaifazheZhinan/js/reader.js
BiteBiKaifazheZhinan/js/reader.js.map
BiteBiKaifazheZhinan/js/reader.min.js
BiteBiKaifazheZhinan/js/reader.min.map
BiteBiKaifazheZhinan/js/hooks/__init__.py
BiteBiKaifazheZhinan/js/hooks/extensions/__init__.py
BiteBiKaifazheZhinan/js/hooks/extensions/highlight.js
BiteBiKaifazheZhinan/js/libs/__init__.py
BiteBiKaifazheZhinan/js/libs/jquery.min.js
BiteBiKaifazheZhinan/js/libs/localforage.min.js
BiteBiKaifazheZhinan/js/libs/screenfull.js
BiteBiKaifazheZhinan/js/libs/screenfull.min.js
BiteBiKaifazheZhinan/js/libs/zip.min.js
BiteBiKaifazheZhinan/js/plugins/__init__.py
BiteBiKaifazheZhinan/js/plugins/hypothesis.js
bite_bi_kaifazhe_zhinan-2024.3.2.0.dist-info/METADATA
bite_bi_kaifazhe_zhinan-2024.3.2.0.dist-info/WHEEL
bite_bi_kaifazhe_zhinan-2024.3.2.0.dist-info/entry_points.txt
bite_bi_kaifazhe_zhinan-2024.3.2.0.dist-info/top_level.txt
bite_bi_kaifazhe_zhinan-2024.3.2.0.dist-info/RECORD
